autojoiner/__init__.py
autojoiner/__main__.py
autojoiner/autojoin.py
autojoiner-0.2.2.dist-info/LICENSE
autojoiner-0.2.2.dist-info/METADATA
autojoiner-0.2.2.dist-info/WHEEL
autojoiner-0.2.2.dist-info/entry_points.txt
autojoiner-0.2.2.dist-info/top_level.txt
autojoiner-0.2.2.dist-info/RECORD
