Metadata-Version: 2.1
Name: autojoiner
Version: 0.2.2
Summary: UNKNOWN
Home-page: https://github.com/rishi255/autojoiner
Author: Rishikesh Rachchh
Author-email: rishikeshrachchh@gmail.com
License: MIT
Platform: UNKNOWN
Classifier: Development Status :: 2 - Pre-Alpha
Classifier: License :: OSI Approved :: MIT License
Requires-Python: >=3.8
Requires-Dist: click
Requires-Dist: selenium
